rmlhrv/__init__.py
rmlhrv/__version__.py
rmlhrv/ecg.py
rmlhrv/factory.py
rmlhrv/get_features.py
rmlhrv/tools.py
rmlhrv/utils.py
rmlhrv-1.0.0.dist-info/LICENSE
rmlhrv-1.0.0.dist-info/METADATA
rmlhrv-1.0.0.dist-info/WHEEL
rmlhrv-1.0.0.dist-info/top_level.txt
rmlhrv-1.0.0.dist-info/RECORD
