Metadata-Version: 2.1
Name: rmlhrv
Version: 1.0.0
Summary: Python toolbox for Heart Rate Variability and Stress Level Analysis.
Home-page: https://github.com/rehmanzafar/rmlhrv.git
Author: Ryerson Multimedia Lab (RML)
Author-email: rml@ryerson.ca
License: UNKNOWN
Keywords: Heart Rate Variability,HRV
Platform: UNKNOWN
Classifier: Intended Audience :: Developers
Classifier: Intended Audience :: Education
Classifier: Intended Audience :: Science/Research
Classifier: Natural Language :: English
Classifier: License :: OSI Approved :: BSD License
Classifier: Programming Language :: Python
Classifier: Programming Language :: Python :: 2.7
Classifier: Programming Language :: Python :: 3
Classifier: Operating System :: OS Independent
Requires-Python: >=2.7
Requires-Dist: matplotlib
Requires-Dist: numpy
Requires-Dist: scipy
Requires-Dist: nolds
